sasktran/__init__.py
sasktran/_version.py
sasktran/atmosphere.py
sasktran/brdf.py
sasktran/climatology.py
sasktran/config.ini
sasktran/conftest.py
sasktran/emission.py
sasktran/emission_hitranphotochemical.py
sasktran/engine.py
sasktran/engine_occ.py
sasktran/exceptions.py
sasktran/geodetic.py
sasktran/geometry.py
sasktran/handles.py
sasktran/lineofsight.py
sasktran/opticalproperty.py
sasktran/solarspectrum.py
sasktran/species.py
sasktran/stokesvector.py
sasktran/test_climatology.py
sasktran/test_emissions.py
sasktran/test_hitran.py
sasktran/test_hr.py
sasktran/test_hr_wf.py
sasktran/test_mc.py
sasktran/test_mie.py
sasktran/test_occ.py
sasktran/test_opticalproperty.py
sasktran/test_species.py
sasktran/util.py
sasktran/aband/__init__.py
sasktran/aband/load_data.py
sasktran/aband/model.py
sasktran/aband/util.py
sasktran/aband/data/HITRANo2.txt
sasktran/aband/data/datHar.txt
sasktran/aband/data/datLya.txt
sasktran/aband/data/datSRC.txt
sasktran/aband/data/msis2.txt
sasktran/co/__init__.py
sasktran/co/engine.py
sasktran/co/tests/__init__.py
sasktran/co/tests/common.py
sasktran/co/tests/hr_comparisons/__init__.py
sasktran/co/tests/hr_comparisons/test_single_scatter.py
sasktran/co/tests/weighting_functions/__init__.py
sasktran/co/tests/weighting_functions/common.py
sasktran/co/tests/weighting_functions/test_do_multiscatter.py
sasktran/co/tests/weighting_functions/test_single_scatter.py
sasktran/config/__init__.py
sasktran/config/update_settings.py
sasktran/databases/__init__.py
sasktran/databases/baum.py
sasktran/disco/__init__.py
sasktran/disco/engine.py
sasktran/disco/interface.py
sasktran/disco/lowlevel/__init__.py
sasktran/disco/lowlevel/definitions.py
sasktran/disco/tests/__init__.py
sasktran/disco/tests/common.py
sasktran/disco/tests/test_basic_operation.py
sasktran/disco/tests/test_greens_function.py
sasktran/disco/tests/test_lowlevel.py
sasktran/disco/tests/test_polarization.py
sasktran/disco/tests/test_polarization_weighting_functions.py
sasktran-1.8.8.dist-info/METADATA
sasktran-1.8.8.dist-info/WHEEL
sasktran-1.8.8.dist-info/top_level.txt
sasktran-1.8.8.dist-info/RECORD
