Metadata-Version: 2.1
Name: sasktran
Version: 1.8.8
Summary: The University of Saskatchewan Radiative Transfer Model
Home-page: https://arg.usask.ca/docs/sasktran/
Author: Daniel Zawada
Author-email: Daniel Zawada <daniel.zawada@usask.ca>
Classifier: Development Status :: 4 - Beta
Classifier: Programming Language :: Python :: 3 :: Only
Classifier: Programming Language :: Python :: 3.10
Classifier: Programming Language :: Python :: 3.11
Classifier: Programming Language :: Python :: 3.12
Requires-Python: >=3.7
Requires-Dist: numpy
Requires-Dist: pyyaml
Requires-Dist: urllib3
Requires-Dist: appdirs
Requires-Dist: packaging
